{
    "name": "Leito Cowgirl 2",
    "modpack": "LeitoAnimations",
    "length": 2,
    "navigations": [
        {
            "destination": "LeitoCowgirl2-5",
            "description": "Next(climax)",
            "icon": "OStim/symbols/climax"
        },
        {
            "destination": "LeitoCowgirl2-3",
            "description": "Back",
            "icon": "OStim/symbols/previous"
        },
        {
            "destination": "LeitoHumanPage1",
            "description": "Return",
            "icon": "OStim/symbols/return"
        }
    ],
    "speeds": [
        {
            "animation": "LeitoCowgirl2_4"
        }
    ],
    "actors": [
        {
            "intendedSex": "male",
            "sosBend": -3,
            "scale": 1,
            "feetOnGround": false,
            "tags": [
                "lyingback"
            ],
            "autoTransitions": {
                "climax": "LeitoCowgirl2-5"
            }
        },
        {
            "intendedSex": "female",
            "scale": 1,
            "feetOnGround": true,
            "tags": [
                "sitting"
            ],
            "autoTransitions": {
                "climax": "LeitoCowgirl2-5"
            }
        }
    ],
    "actions": [
        {
            "type": "vaginalsex",
            "actor": 0,
            "target": 1
        },
        {
            "type": "holdingleg",
            "actor": 0,
            "target": 1
        },
        {
            "type": "femalemasturbation",
            "actor": 1
        }
    ],
    "tags": [
        "leito",
        "cowgirl"
    ]
}